{
  "experiment": "real_code2hyp_multilabel_pilot",
  "interpretation_status": "real_data_pilot_not_final_claim",
  "dataset": {
    "train_path": "data/code2seq_java_small/java-small/java-small.train.c2s",
    "validation_path": "data/code2seq_java_small/java-small/java-small.val.c2s",
    "train_records": 512,
    "validation_records_loaded": 128,
    "validation_records_after_known_target_filter": 53,
    "target_subtoken_vocab_size": 608,
    "token_vocab_size": 3,
    "ast_node_vocab_size": 166,
    "path_encoder": "gru",
    "representation_transform": "identity",
    "lexical_ablation": "structural_only"
  },
  "training": {
    "epochs": 3,
    "batch_size": 64,
    "learning_rate": 0.003,
    "structural_loss_weight_for_B5": 0.05,
    "structural_regularizer_for_B5": "rank",
    "use_positive_weighting": true,
    "max_positive_weight": 20.0,
    "positive_weight_mean": 19.933841705322266,
    "positive_weight_max": 20.0,
    "curvature": 1.0,
    "model_seeds": [
      101,
      202,
      303
    ],
    "variant_filter": [
      "B29_hyperbolic_path_dual_attention_mp_separated"
    ],
    "metric": "target-subtoken micro precision/recall/F1 with top-k = true target subtoken count"
  },
  "runs": [
    {
      "variant": "B29_hyperbolic_path_dual_attention_mp_separated",
      "model_seed": 101,
      "parameter_count": 76064,
      "initial_validation_f1": 0.0,
      "validation_precision": 0.23863636363636365,
      "validation_recall": 0.23863636363636365,
      "validation_f1": 0.23863636363636365,
      "final_train_loss": 0.36148156970739365,
      "final_train_f1": 0.1383119165633946,
      "history": [
        {
          "epoch": 1.0,
          "loss": 0.7173902094364166,
          "task_loss": 0.7173902094364166,
          "structural_loss": 0.0,
          "precision": 0.03328460966143897,
          "recall": 0.03328460966143897,
          "f1": 0.033284609661438966,
          "curvature": 1.0,
          "structural_loss_weight": 0.016666666666666666
        },
        {
          "epoch": 2.0,
          "loss": 0.5534312836825848,
          "task_loss": 0.5534312836825848,
          "structural_loss": 0.0,
          "precision": 0.1132927807132827,
          "recall": 0.1132927807132827,
          "f1": 0.11329278071328269,
          "curvature": 1.0,
          "structural_loss_weight": 0.03333333333333333
        },
        {
          "epoch": 3.0,
          "loss": 0.36148156970739365,
          "task_loss": 0.36148156970739365,
          "structural_loss": 0.0,
          "precision": 0.1383119165633946,
          "recall": 0.1383119165633946,
          "f1": 0.1383119165633946,
          "curvature": 1.0,
          "structural_loss_weight": 0.05000000000000001
        }
      ],
      "validation_structural_loss": 0.13263840973377228,
      "validation_structural_rank_loss": 0.45431190729141235,
      "validation_structural_spearman": 0.1859521120786667,
      "structural_loss_weight": 0.05,
      "structural_loss_schedule": "linear",
      "structural_regularizer": "path_dual_attention_separation",
      "curvature": 1.0,
      "factorized_metric_weights": [
        1.0,
        1.0
      ],
      "factorized_channel_mixer_rank": 0
    },
    {
      "variant": "B29_hyperbolic_path_dual_attention_mp_separated",
      "model_seed": 202,
      "parameter_count": 76064,
      "initial_validation_f1": 0.0,
      "validation_precision": 0.14772727272727273,
      "validation_recall": 0.14772727272727273,
      "validation_f1": 0.14772727272727273,
      "final_train_loss": 0.36286767572164536,
      "final_train_f1": 0.158565082395775,
      "history": [
        {
          "epoch": 1.0,
          "loss": 0.7188072353601456,
          "task_loss": 0.7188072353601456,
          "structural_loss": 0.0,
          "precision": 0.0463998534339096,
          "recall": 0.0463998534339096,
          "f1": 0.0463998534339096,
          "curvature": 1.0,
          "structural_loss_weight": 0.016666666666666666
        },
        {
          "epoch": 2.0,
          "loss": 0.5607963725924492,
          "task_loss": 0.5607963725924492,
          "structural_loss": 0.0,
          "precision": 0.14043478832602974,
          "recall": 0.14043478832602974,
          "f1": 0.14043478832602976,
          "curvature": 1.0,
          "structural_loss_weight": 0.03333333333333333
        },
        {
          "epoch": 3.0,
          "loss": 0.36286767572164536,
          "task_loss": 0.36286767572164536,
          "structural_loss": 0.0,
          "precision": 0.158565082395775,
          "recall": 0.158565082395775,
          "f1": 0.158565082395775,
          "curvature": 1.0,
          "structural_loss_weight": 0.05000000000000001
        }
      ],
      "validation_structural_loss": 0.14268448948860168,
      "validation_structural_rank_loss": 0.2912781536579132,
      "validation_structural_spearman": 0.06405593454837799,
      "structural_loss_weight": 0.05,
      "structural_loss_schedule": "linear",
      "structural_regularizer": "path_dual_attention_separation",
      "curvature": 1.0,
      "factorized_metric_weights": [
        1.0,
        1.0
      ],
      "factorized_channel_mixer_rank": 0
    },
    {
      "variant": "B29_hyperbolic_path_dual_attention_mp_separated",
      "model_seed": 303,
      "parameter_count": 76064,
      "initial_validation_f1": 0.0,
      "validation_precision": 0.17045454545454544,
      "validation_recall": 0.17045454545454544,
      "validation_f1": 0.17045454545454544,
      "final_train_loss": 0.3604441285133362,
      "final_train_f1": 0.1401796351431723,
      "history": [
        {
          "epoch": 1.0,
          "loss": 0.7187492027878761,
          "task_loss": 0.7187492027878761,
          "structural_loss": 0.0,
          "precision": 0.03120739901425781,
          "recall": 0.03120739901425781,
          "f1": 0.03120739901425781,
          "curvature": 1.0,
          "structural_loss_weight": 0.016666666666666666
        },
        {
          "epoch": 2.0,
          "loss": 0.5519263111054897,
          "task_loss": 0.5519263111054897,
          "structural_loss": 0.0,
          "precision": 0.08341132217881544,
          "recall": 0.08341132217881544,
          "f1": 0.08341132217881544,
          "curvature": 1.0,
          "structural_loss_weight": 0.03333333333333333
        },
        {
          "epoch": 3.0,
          "loss": 0.3604441285133362,
          "task_loss": 0.3604441285133362,
          "structural_loss": 0.0,
          "precision": 0.1401796351431723,
          "recall": 0.1401796351431723,
          "f1": 0.1401796351431723,
          "curvature": 1.0,
          "structural_loss_weight": 0.05000000000000001
        }
      ],
      "validation_structural_loss": 0.13362397253513336,
      "validation_structural_rank_loss": 0.29091784358024597,
      "validation_structural_spearman": 0.10139356553554535,
      "structural_loss_weight": 0.05,
      "structural_loss_schedule": "linear",
      "structural_regularizer": "path_dual_attention_separation",
      "curvature": 1.0,
      "factorized_metric_weights": [
        1.0,
        1.0
      ],
      "factorized_channel_mixer_rank": 0
    }
  ],
  "claim_boundary": "This is a real-data pilot on code2vec/code2seq preprocessed files. It is suitable for debugging the scientific pipeline, but final article claims require the preregistered full split and statistical analysis.",
  "archive_status": {
    "path": "data/code2seq_java_small/java-small-preprocessed.tar.gz",
    "exists": true,
    "bytes": 479663374,
    "size_matches": true
  },
  "inventory": {
    "root": "data/code2seq_java_small",
    "split_paths": {
      "train": "data/code2seq_java_small/java-small/java-small.train.c2s",
      "val": "data/code2seq_java_small/java-small/java-small.val.c2s",
      "test": "data/code2seq_java_small/java-small/java-small.test.c2s"
    },
    "split_line_counts": {
      "train": 691974,
      "val": 23844,
      "test": 57088
    }
  }
}
